2024_old_requirements.txt
LICENSE.txt
MANIFEST.in
README.md
__init__.py
notes.txt
setup.cfg
setup.py
tests.py
dist/moon-1.0.1.tar.gz
dist/moon-1.0.2.tar.gz
dist/moon-1.0.3.tar.gz
dist/moon-1.0.4.tar.gz
dist/moon-1.0.5.tar.gz
dist/moon-1.0.6.tar.gz
dist/moon-1.0.7.tar.gz
dist/moon-1.0.8.tar.gz
dist/moon-1.0.9.tar.gz
dist/moon-1.1.0.tar.gz
dist/moon-1.1.1.tar.gz
dist/moon-1.1.2.tar.gz
dist/moon-1.1.3.tar.gz
dist/moon-1.1.4.tar.gz
dist/moon-1.1.5.tar.gz
dist/moon-1.1.6.tar.gz
dist/moon-1.1.7.tar.gz
dist/moon-1.1.8.tar.gz
dist/moon-1.1.9.tar.gz
moon/__init__.py
moon/custom_image.py
moon/dialamoon.py
moon/jupyter_ui.py
moon/requirements.txt
moon/terminal_ui.py
moon.egg-info/PKG-INFO
moon.egg-info/SOURCES.txt
moon.egg-info/dependency_links.txt
moon.egg-info/requires.txt
moon.egg-info/top_level.txt
moon/res/__init__.py
moon/res/constants.json
moon/res/en/__init__.py
moon/res/en/ui_messages.py
moon/tests/__init__.py
moon/tests/cache.py
moon/tests/general.py