Metadata-Version: 2.1
Name: moon
Version: 2.0.0
Summary: Gets moon visualizations courtesy of SVS, NASA, Ernie Wright
Home-page: https://github.com/spacerest/moon
Author: Sadie Parker
Author-email: sadiemparker@gmail.com
License: MIT
Download-URL: https://github.com/spacerest/moon/archive/v_2_0_0.tar.gz
Keywords: MOON,ART,NASA,DIALAMOON
Platform: UNKNOWN
Classifier: Development Status :: 4 - Beta
Classifier: Intended Audience :: Other Audience
Classifier: Topic :: Software Development :: Build Tools
Classifier: License :: OSI Approved :: MIT License
Classifier: Programming Language :: Python :: 3
Classifier: Programming Language :: Python :: 3.4
Classifier: Programming Language :: Python :: 3.5
Classifier: Programming Language :: Python :: 3.6
Classifier: Programming Language :: Python :: 3.7
Classifier: Programming Language :: Python :: 3.8
Classifier: Programming Language :: Python :: 3.9
Classifier: Programming Language :: Python :: 3.10
License-File: LICENSE.txt
